generativepoetry/__init__.py
generativepoetry/decomposer.py
generativepoetry/jolastic.py
generativepoetry/lexigen.py
generativepoetry/pdf.py
generativepoetry/poemgen.py
generativepoetry/utils.py
generativepoetry/data/abbreviations_etc.txt
generativepoetry/data/hate_words.txt
generativepoetry-0.3.4.data/scripts/generative-poetry-cli
generativepoetry-0.3.4.dist-info/LICENSE
generativepoetry-0.3.4.dist-info/METADATA
generativepoetry-0.3.4.dist-info/WHEEL
generativepoetry-0.3.4.dist-info/dependency_links.txt
generativepoetry-0.3.4.dist-info/top_level.txt
generativepoetry-0.3.4.dist-info/zip-safe
generativepoetry-0.3.4.dist-info/RECORD
