Metadata-Version: 2.1
Name: generativepoetry
Version: 0.3.4
Summary: A library primarily for procedurally generating visual poems
Home-page: https://github.com/coreybobco/generativepoetry-py
Author: Corey Bobco
Author-email: corey.bobco@gmail.com
License: MIT
Keywords: poetry
Platform: UNKNOWN
Classifier: Development Status :: 3 - Alpha
Classifier: License :: OSI Approved :: BSD License
Classifier: Programming Language :: Python :: 3
Classifier: Programming Language :: Python :: 3.6
Classifier: Programming Language :: Python :: 3.7
Classifier: Intended Audience :: Developers
Classifier: Intended Audience :: Education
Classifier: Intended Audience :: Science/Research
Classifier: License :: OSI Approved :: MIT License
Classifier: Natural Language :: English
Classifier: Topic :: Artistic Software
Requires-Dist: console-menu (==0.6.0)
Requires-Dist: Gutenberg (==0.8.0)
Requires-Dist: hunspell (>=0.5.5)
Requires-Dist: inflect (==4.1.0)
Requires-Dist: internetarchive (==1.8.5)
Requires-Dist: markovify (==0.8.0)
Requires-Dist: nltk (==3.4.5)
Requires-Dist: pdf2image (==1.12.1)
Requires-Dist: rdflib (==4.2.2)
Requires-Dist: pronouncing (>=0.2.0)
Requires-Dist: python-datamuse (>=1.3.0)
Requires-Dist: spacy (>=2.2.3)
Requires-Dist: reportlab (>=3.5.26)
Requires-Dist: unittest2 (==1.1.0)
Requires-Dist: wordfreq (>=2.2.2)
